CHANGES.txt
README.txt
setup.py
Products/__init__.py
Products.SignupSheet.egg-info/PKG-INFO
Products.SignupSheet.egg-info/SOURCES.txt
Products.SignupSheet.egg-info/dependency_links.txt
Products.SignupSheet.egg-info/namespace_packages.txt
Products.SignupSheet.egg-info/not-zip-safe
Products.SignupSheet.egg-info/requires.txt
Products.SignupSheet.egg-info/top_level.txt
Products/SignupSheet/LICENSE.txt
Products/SignupSheet/TODO.txt
Products/SignupSheet/__init__.py
Products/SignupSheet/config.py
Products/SignupSheet/configure.zcml
Products/SignupSheet/events.py
Products/SignupSheet/interfaces.py
Products/SignupSheet/setuphandlers.py
Products/SignupSheet/version.txt
Products/SignupSheet/Extensions/__init__.py
Products/SignupSheet/Extensions/migrate.py
Products/SignupSheet/Extensions/signupsheet_registrant_workflow_scripts.py
Products/SignupSheet/content/__init__.py
Products/SignupSheet/content/registrant.py
Products/SignupSheet/content/signupsheet.py
Products/SignupSheet/i18n/manual.pot
Products/SignupSheet/i18n/runi18ndude.sh
Products/SignupSheet/i18n/signupsheet-cs.po
Products/SignupSheet/i18n/signupsheet-de.po
Products/SignupSheet/i18n/signupsheet-eu.po
Products/SignupSheet/i18n/signupsheet-fr.po
Products/SignupSheet/i18n/signupsheet-it.po
Products/SignupSheet/i18n/signupsheet-no.po
Products/SignupSheet/i18n/signupsheet-plone-cs.po
Products/SignupSheet/i18n/signupsheet-plone-de.po
Products/SignupSheet/i18n/signupsheet-plone-it.po
Products/SignupSheet/i18n/signupsheet-plone-no.po
Products/SignupSheet/i18n/signupsheet-plone-pt-br.po
Products/SignupSheet/i18n/signupsheet-plone.pot
Products/SignupSheet/i18n/signupsheet-pt-br.po
Products/SignupSheet/i18n/signupsheet.pot
Products/SignupSheet/profiles/default/cmfformcontroller.xml
Products/SignupSheet/profiles/default/factorytool.xml
Products/SignupSheet/profiles/default/import_steps.xml
Products/SignupSheet/profiles/default/metadata.xml
Products/SignupSheet/profiles/default/products_signupsheet_various.txt
Products/SignupSheet/profiles/default/propertiestool.xml
Products/SignupSheet/profiles/default/rolemap.xml
Products/SignupSheet/profiles/default/skins.xml
Products/SignupSheet/profiles/default/tinymce.xml
Products/SignupSheet/profiles/default/types.xml
Products/SignupSheet/profiles/default/workflows.xml
