Metadata-Version: 1.0
Name: Products.SignupSheet
Version: 0.6.0
Summary: A signup sheet implementation for Plone
Home-page: http://plone.org/products/signupsheet
Author: RedTurtle Technology
Author-email: sviluppoplone@redturtle.it
License: GPL2
Keywords: Archetypes Plone Zope Python PloneGov
Platform: UNKNOWN
Classifier: Programming Language :: Python
Classifier: Framework :: Zope2
Classifier: Framework :: Plone
Classifier: Development Status :: 4 - Beta
Classifier: License :: OSI Approved :: GNU General Public License (GPL)
